pybiomart/__init__.py
pybiomart/base.py
pybiomart/dataset.py
pybiomart/mart.py
pybiomart/server.py
pybiomart-0.2.0.dist-info/DESCRIPTION.rst
pybiomart-0.2.0.dist-info/METADATA
pybiomart-0.2.0.dist-info/RECORD
pybiomart-0.2.0.dist-info/WHEEL
pybiomart-0.2.0.dist-info/metadata.json
pybiomart-0.2.0.dist-info/top_level.txt
pybiomart-0.2.0.dist-info/zip-safe
