Metadata-Version: 1.1
Name: pybiomart
Version: 0.2.0
Summary: A simple pythonic interface to biomart.
Home-page: https://github.com/jrderuiter/pybiomart
Author: Julian de Ruiter
Author-email: julianderuiter@gmail.com
License: MIT
Platform: UNKNOWN
Classifier: Intended Audience :: Developers
Classifier: Intended Audience :: Science/Research
Classifier: License :: OSI Approved :: MIT License
Classifier: Operating System :: OS Independent
Classifier: Programming Language :: Python :: 2.7
Classifier: Programming Language :: Python :: 3.4
Classifier: Programming Language :: Python :: 3.5
